aioapp_http/__init__.py
tests/__init__.py
tests/conftest.py
tests/test_http.py
aioapp_http-0.0.1b7.dist-info/AUTHORS.rst
aioapp_http-0.0.1b7.dist-info/LICENSE
aioapp_http-0.0.1b7.dist-info/METADATA
aioapp_http-0.0.1b7.dist-info/WHEEL
aioapp_http-0.0.1b7.dist-info/top_level.txt
aioapp_http-0.0.1b7.dist-info/RECORD
